rogueui/example.py
rogue_ui-0.0.0.dist-info/METADATA
rogue_ui-0.0.0.dist-info/WHEEL
rogue_ui-0.0.0.dist-info/top_level.txt
rogue_ui-0.0.0.dist-info/RECORD
