Metadata-Version: 2.4
Name: rogue-ui
Version: 0.0.0
Summary: An object oriented take on frontend
Author-email: Özgen Eren <ozgeneren@gmail.com>
